studytool/__init__.py
studytool/ebook.py
studytool/link.py
studytool/main.py
studytool/num_to_image_path.py
studytool/pdf2text.py
studytool/pdf_merge.py
studytool/slides2md.py
studytool/trad_to_simp.py
studytool/youtube.py
studytool/youtube_playlist.py
studytool-0.1.19.dist-info/METADATA
studytool-0.1.19.dist-info/WHEEL
studytool-0.1.19.dist-info/entry_points.txt
studytool-0.1.19.dist-info/licenses/LICENSE
studytool-0.1.19.dist-info/RECORD
