Metadata-Version: 2.4
Name: studytool
Version: 0.1.19
Summary: A comprehensive command-line study toolkit for PDF processing, video downloading, and text conversion.
Author: Sihan A
License: MIT
License-File: LICENSE
Requires-Python: >=3.12
Requires-Dist: beautifulsoup4>=4.13.4
Requires-Dist: click>=8.2.1
Requires-Dist: ebooklib>=0.19
Requires-Dist: opencc>=1.1.9
Requires-Dist: pdf2image>=1.16.3
Requires-Dist: pymupdf>=1.26.0
Requires-Dist: pypdf2>=3.0.1
Requires-Dist: pytube>=15.0.0
Requires-Dist: requests>=2.32.3
Requires-Dist: rich>=13.6.0
Requires-Dist: tqdm>=4.66.1
Requires-Dist: typer>=0.16.0
Requires-Dist: youtube-dl>=2021.12.17
Requires-Dist: yt-dlp>=2025.5.22
Provides-Extra: dev
Requires-Dist: black>=23.10.1; extra == 'dev'
Requires-Dist: flake8>=6.1.0; extra == 'dev'
Requires-Dist: pre-commit>=3.5.0; extra == 'dev'
